rubixinsights/__init__.py
rubixinsights/dwh.py
rubixinsights/helper.py
rubixinsights/initializer.py
rubixinsights/metadata.py
rubixinsights/secrets_engine.py
rubixinsights/slack.py
rubixinsights/sqs.py
rubixinsights-0.0.36.dist-info/WHEEL
rubixinsights-0.0.36.dist-info/METADATA
rubixinsights-0.0.36.dist-info/RECORD
