Metadata-Version: 2.1
Name: rubixinsights
Version: 0.0.36
Summary: rubixin-sights
Author: rubix
Requires-Python: >=3.7.1,<4
Classifier: Programming Language :: Python :: 3
Classifier: Programming Language :: Python :: 3.10
Classifier: Programming Language :: Python :: 3.8
Classifier: Programming Language :: Python :: 3.9
Requires-Dist: Jinja2 (>=2.11.0,<3.0.0)
Requires-Dist: PyYAML (==5.3.1)
Requires-Dist: SQLAlchemy (==1.3.23)
Requires-Dist: boto3 (>=1.15.0,<2.0.0)
Requires-Dist: google-api-core (==1.26.0)
Requires-Dist: google-api-python-client (==1.12.8)
Requires-Dist: google-auth-httplib2 (==0.0.4)
Requires-Dist: google-auth-oauthlib (==0.4.2)
Requires-Dist: googleapis-common-protos (==1.52.0)
Requires-Dist: loguru (>=0.5.3,<0.6.0)
Requires-Dist: pandas (==1.2.0)
Requires-Dist: psycopg2-binary (==2.8.6)
Requires-Dist: requests (==2.25.1)
